Metadata-Version: 2.1
Name: webchat
Version: 0.0.2
Summary: webchat
Home-page: https://github.com/fiefdx/WebChat
Author: fiefdx
Author-email: fiefdx@163.com
License: MIT
Platform: UNKNOWN
Classifier: License :: OSI Approved :: MIT License
Classifier: Programming Language :: Python :: 3
Classifier: Programming Language :: Python :: 3.7
Requires-Dist: tornado
Requires-Dist: pyYAML
